{
"type": "FeatureCollection",
"crs": { "type": "name", "properties": { "name": "urn:ogc:def:crs:OGC:1.3:CRS84" } },
                                                                                
"features": [
{ "type": "Feature", "id": 34870, "properties": { "state": "West Virginia", "endyear": 2013.000000, "casvol": 18.000000 }, "geometry": { "type": "Point", "coordinates": [ -80.012237909865078, 39.21256552319705 ] } },
{ "type": "Feature", "id": 34879, "properties": { "state": "West Virginia", "endyear": 2014.000000, "casvol": 26.000000 }, "geometry": { "type": "Point", "coordinates": [ -80.17202987398079, 38.787357482683454 ] } },
{ "type": "Feature", "id": 34882, "properties": { "state": "West Virginia", "endyear": 2014.000000, "casvol": 0.000000 }, "geometry": { "type": "Point", "coordinates": [ -80.649671737481626, 39.976192538186417 ] } },
{ "type": "Feature", "id": 34884, "properties": { "state": "West Virginia", "endyear": 2014.000000, "casvol": 0.000000 }, "geometry": { "type": "Point", "coordinates": [ -80.622053335037876, 40.251782523588041 ] } },
{ "type": "Feature", "id": 34885, "properties": { "state": "West Virginia", "endyear": 2014.000000, "casvol": 0.000000 }, "geometry": { "type": "Point", "coordinates": [ -80.617013469368771, 39.917102254220509 ] } },
{ "type": "Feature", "id": 34886, "properties": { "state": "West Virginia", "endyear": 2014.000000, "casvol": 0.000000 }, "geometry": { "type": "Point", "coordinates": [ -80.616973466528663, 39.91712525409379 ] } },
{ "type": "Feature", "id": 34888, "properties": { "state": "West Virginia", "endyear": 2013.000000, "casvol": 0.000000 }, "geometry": { "type": "Point", "coordinates": [ -80.51162657383577, 39.189221256839645 ] } },
{ "type": "Feature", "id": 34898, "properties": { "state": "West Virginia", "endyear": 2014.000000, "casvol": 36.000000 }, "geometry": { "type": "Point", "coordinates": [ -80.054826084196648, 39.201620999660243 ] } },
{ "type": "Feature", "id": 34899, "properties": { "state": "West Virginia", "endyear": 2014.000000, "casvol": 48.000000 }, "geometry": { "type": "Point", "coordinates": [ -80.054782082487606, 39.20157800165326 ] } },
{ "type": "Feature", "id": 34900, "properties": { "state": "West Virginia", "endyear": 2014.000000, "casvol": 39.000000 }, "geometry": { "type": "Point", "coordinates": [ -80.054739080808361, 39.20153500362715 ] } },
{ "type": "Feature", "id": 34901, "properties": { "state": "West Virginia", "endyear": 2014.000000, "casvol": 17.000000 }, "geometry": { "type": "Point", "coordinates": [ -80.441707579323293, 39.061942848588252 ] } },
{ "type": "Feature", "id": 34922, "properties": { "state": "West Virginia", "endyear": 2013.000000, "casvol": 0.000000 }, "geometry": { "type": "Point", "coordinates": [ -80.553457614649986, 39.222432804968186 ] } },
{ "type": "Feature", "id": 34923, "properties": { "state": "West Virginia", "endyear": 2013.000000, "casvol": 0.000000 }, "geometry": { "type": "Point", "coordinates": [ -80.553424213286519, 39.222424905734506 ] } },
{ "type": "Feature", "id": 34929, "properties": { "state": "West Virginia", "endyear": 2014.000000, "casvol": 0.000000 }, "geometry": { "type": "Point", "coordinates": [ -80.489466001440164, 39.201590287161643 ] } },
{ "type": "Feature", "id": 34930, "properties": { "state": "West Virginia", "endyear": 2014.000000, "casvol": 0.000000 }, "geometry": { "type": "Point", "coordinates": [ -80.489516003485207, 39.201629285911864 ] } },
{ "type": "Feature", "id": 34931, "properties": { "state": "West Virginia", "endyear": 2014.000000, "casvol": 0.000000 }, "geometry": { "type": "Point", "coordinates": [ -80.489491002455537, 39.201609286547452 ] } },
{ "type": "Feature", "id": 34932, "properties": { "state": "West Virginia", "endyear": 2013.000000, "casvol": 0.000000 }, "geometry": { "type": "Point", "coordinates": [ -80.553524217388144, 39.222449903410876 ] } },
{ "type": "Feature", "id": 34933, "properties": { "state": "West Virginia", "endyear": 2013.000000, "casvol": 0.000000 }, "geometry": { "type": "Point", "coordinates": [ -80.553490816018908, 39.222441604185896 ] } },
{ "type": "Feature", "id": 34964, "properties": { "state": "West Virginia", "endyear": 2014.000000, "casvol": 0.000000 }, "geometry": { "type": "Point", "coordinates": [ -80.46627693407315, 39.238067475380575 ] } },
{ "type": "Feature", "id": 34982, "properties": { "state": "West Virginia", "endyear": 2014.000000, "casvol": 26.000000 }, "geometry": { "type": "Point", "coordinates": [ -80.848734486587759, 39.274724343129826 ] } },
{ "type": "Feature", "id": 34985, "properties": { "state": "West Virginia", "endyear": 2014.000000, "casvol": 0.000000 }, "geometry": { "type": "Point", "coordinates": [ -80.578312524299392, 39.386518413808801 ] } },
{ "type": "Feature", "id": 34986, "properties": { "state": "West Virginia", "endyear": 2014.000000, "casvol": 0.000000 }, "geometry": { "type": "Point", "coordinates": [ -80.578276522724508, 39.38652141439669 ] } },
{ "type": "Feature", "id": 34987, "properties": { "state": "West Virginia", "endyear": 2014.000000, "casvol": 0.000000 }, "geometry": { "type": "Point", "coordinates": [ -80.578240521149638, 39.386524414984578 ] } },
{ "type": "Feature", "id": 34988, "properties": { "state": "West Virginia", "endyear": 2014.000000, "casvol": 0.000000 }, "geometry": { "type": "Point", "coordinates": [ -80.7327832358161, 39.365850017476355 ] } },
{ "type": "Feature", "id": 34989, "properties": { "state": "West Virginia", "endyear": 2014.000000, "casvol": 0.000000 }, "geometry": { "type": "Point", "coordinates": [ -80.732797236170342, 39.365905016303522 ] } },
{ "type": "Feature", "id": 34990, "properties": { "state": "West Virginia", "endyear": 2014.000000, "casvol": 0.000000 }, "geometry": { "type": "Point", "coordinates": [ -80.732806236442258, 39.365930015723464 ] } },
{ "type": "Feature", "id": 34991, "properties": { "state": "West Virginia", "endyear": 2014.000000, "casvol": 0.000000 }, "geometry": { "type": "Point", "coordinates": [ -80.620621085263949, 39.219476674889748 ] } },
{ "type": "Feature", "id": 34992, "properties": { "state": "West Virginia", "endyear": 2014.000000, "casvol": 0.000000 }, "geometry": { "type": "Point", "coordinates": [ -80.62059608403915, 39.219456675781764 ] } },
{ "type": "Feature", "id": 34993, "properties": { "state": "West Virginia", "endyear": 2014.000000, "casvol": 0.000000 }, "geometry": { "type": "Point", "coordinates": [ -80.620571082785446, 39.2194346767185 ] } },
{ "type": "Feature", "id": 34994, "properties": { "state": "West Virginia", "endyear": 2014.000000, "casvol": 0.000000 }, "geometry": { "type": "Point", "coordinates": [ -80.474407583320939, 39.203668366476251 ] } },
{ "type": "Feature", "id": 34995, "properties": { "state": "West Virginia", "endyear": 2014.000000, "casvol": 0.000000 }, "geometry": { "type": "Point", "coordinates": [ -80.474387583041022, 39.203690366160629 ] } },
{ "type": "Feature", "id": 34997, "properties": { "state": "West Virginia", "endyear": 2014.000000, "casvol": 1.000000 }, "geometry": { "type": "Point", "coordinates": [ -80.901026325776428, 39.1954520122312 ] } },
{ "type": "Feature", "id": 34998, "properties": { "state": "West Virginia", "endyear": 2014.000000, "casvol": 1.000000 }, "geometry": { "type": "Point", "coordinates": [ -80.901096327425179, 39.195439011174024 ] } },
{ "type": "Feature", "id": 35005, "properties": { "state": "West Virginia", "endyear": 2014.000000, "casvol": 0.000000 }, "geometry": { "type": "Point", "coordinates": [ -80.474368582790859, 39.203712365836751 ] } },
{ "type": "Feature", "id": 35027, "properties": { "state": "West Virginia", "endyear": 2013.000000, "casvol": 2.000000 }, "geometry": { "type": "Point", "coordinates": [ -80.626853026252249, 40.161492816909906 ] } },
{ "type": "Feature", "id": 35054, "properties": { "state": "West Virginia", "endyear": 2014.000000, "casvol": 55.000000 }, "geometry": { "type": "Point", "coordinates": [ -80.787039623352101, 39.831700799605159 ] } },
{ "type": "Feature", "id": 35055, "properties": { "state": "West Virginia", "endyear": 2014.000000, "casvol": 41.000000 }, "geometry": { "type": "Point", "coordinates": [ -80.787117632773473, 39.831444802769809 ] } },
{ "type": "Feature", "id": 35059, "properties": { "state": "West Virginia", "endyear": 2014.000000, "casvol": 50.000000 }, "geometry": { "type": "Point", "coordinates": [ -80.787067626845541, 39.831603800826144 ] } },
{ "type": "Feature", "id": 35060, "properties": { "state": "West Virginia", "endyear": 2014.000000, "casvol": 40.000000 }, "geometry": { "type": "Point", "coordinates": [ -80.787050624809424, 39.831658800149562 ] } },
{ "type": "Feature", "id": 35063, "properties": { "state": "West Virginia", "endyear": 2014.000000, "casvol": 36.000000 }, "geometry": { "type": "Point", "coordinates": [ -80.992781615942803, 39.335106592209669 ] } },
{ "type": "Feature", "id": 35064, "properties": { "state": "West Virginia", "endyear": 2014.000000, "casvol": 26.000000 }, "geometry": { "type": "Point", "coordinates": [ -80.992687613763351, 39.335128593643702 ] } },
{ "type": "Feature", "id": 35070, "properties": { "state": "West Virginia", "endyear": 2014.000000, "casvol": 41.000000 }, "geometry": { "type": "Point", "coordinates": [ -80.528853105848441, 40.000859794809784 ] } },
{ "type": "Feature", "id": 35072, "properties": { "state": "West Virginia", "endyear": 2014.000000, "casvol": 41.000000 }, "geometry": { "type": "Point", "coordinates": [ -80.552855471213121, 40.008284517608949 ] } },
{ "type": "Feature", "id": 35076, "properties": { "state": "West Virginia", "endyear": 2014.000000, "casvol": 62.000000 }, "geometry": { "type": "Point", "coordinates": [ -80.552803494311334, 40.000883632657398 ] } },
{ "type": "Feature", "id": 35077, "properties": { "state": "West Virginia", "endyear": 2014.000000, "casvol": 50.000000 }, "geometry": { "type": "Point", "coordinates": [ -80.552750491280747, 40.000871633201399 ] } },
{ "type": "Feature", "id": 35078, "properties": { "state": "West Virginia", "endyear": 2014.000000, "casvol": 53.000000 }, "geometry": { "type": "Point", "coordinates": [ -80.552905500140483, 40.000907631596483 ] } },
{ "type": "Feature", "id": 35079, "properties": { "state": "West Virginia", "endyear": 2014.000000, "casvol": 23.000000 }, "geometry": { "type": "Point", "coordinates": [ -80.792064466281801, 39.85038342197705 ] } },
{ "type": "Feature", "id": 35080, "properties": { "state": "West Virginia", "endyear": 2014.000000, "casvol": 31.000000 }, "geometry": { "type": "Point", "coordinates": [ -80.79203346400142, 39.850417421831409 ] } },
{ "type": "Feature", "id": 35081, "properties": { "state": "West Virginia", "endyear": 2014.000000, "casvol": 33.000000 }, "geometry": { "type": "Point", "coordinates": [ -80.79194245725958, 39.850519421367402 ] } },
{ "type": "Feature", "id": 35082, "properties": { "state": "West Virginia", "endyear": 2014.000000, "casvol": 38.000000 }, "geometry": { "type": "Point", "coordinates": [ -80.791911454978944, 39.850553421221484 ] } },
{ "type": "Feature", "id": 35083, "properties": { "state": "West Virginia", "endyear": 2014.000000, "casvol": 33.000000 }, "geometry": { "type": "Point", "coordinates": [ -80.791972459533611, 39.850483421559503 ] } },
{ "type": "Feature", "id": 35085, "properties": { "state": "West Virginia", "endyear": 2014.000000, "casvol": 20.000000 }, "geometry": { "type": "Point", "coordinates": [ -80.792003461792461, 39.850450421688826 ] } },
{ "type": "Feature", "id": 35101, "properties": { "state": "West Virginia", "endyear": 2013.000000, "casvol": 0.000000 }, "geometry": { "type": "Point", "coordinates": [ -80.479202273852906, 39.265811031830658 ] } },
{ "type": "Feature", "id": 35102, "properties": { "state": "West Virginia", "endyear": 2013.000000, "casvol": 0.000000 }, "geometry": { "type": "Point", "coordinates": [ -80.479235574960114, 39.265802931769613 ] } },
{ "type": "Feature", "id": 35140, "properties": { "state": "West Virginia", "endyear": 2013.000000, "casvol": 0.000000 }, "geometry": { "type": "Point", "coordinates": [ -80.088226447647443, 39.356553028290563 ] } },
{ "type": "Feature", "id": 35141, "properties": { "state": "West Virginia", "endyear": 2013.000000, "casvol": 0.000000 }, "geometry": { "type": "Point", "coordinates": [ -80.08829138822837, 39.356619994871572 ] } },
{ "type": "Feature", "id": 35142, "properties": { "state": "West Virginia", "endyear": 2013.000000, "casvol": 0.000000 }, "geometry": { "type": "Point", "coordinates": [ -80.088121384156523, 39.356530000571105 ] } },
{ "type": "Feature", "id": 35185, "properties": { "state": "West Virginia", "endyear": 2014.000000, "casvol": 29.000000 }, "geometry": { "type": "Point", "coordinates": [ -80.825407957146055, 39.242633374765703 ] } },
{ "type": "Feature", "id": 35186, "properties": { "state": "West Virginia", "endyear": 2014.000000, "casvol": 15.000000 }, "geometry": { "type": "Point", "coordinates": [ -80.825444956808553, 39.242525376582378 ] } },
{ "type": "Feature", "id": 35187, "properties": { "state": "West Virginia", "endyear": 2014.000000, "casvol": 34.000000 }, "geometry": { "type": "Point", "coordinates": [ -80.825384957159713, 39.242682374061033 ] } },
{ "type": "Feature", "id": 35188, "properties": { "state": "West Virginia", "endyear": 2014.000000, "casvol": 31.000000 }, "geometry": { "type": "Point", "coordinates": [ -80.825422956876963, 39.242577375788244 ] } },
{ "type": "Feature", "id": 35189, "properties": { "state": "West Virginia", "endyear": 2014.000000, "casvol": 39.000000 }, "geometry": { "type": "Point", "coordinates": [ -80.825465956685335, 39.24247037746602 ] } },
{ "type": "Feature", "id": 35190, "properties": { "state": "West Virginia", "endyear": 2014.000000, "casvol": 53.000000 }, "geometry": { "type": "Point", "coordinates": [ -80.548201014236284, 39.973261430718374 ] } },
{ "type": "Feature", "id": 35191, "properties": { "state": "West Virginia", "endyear": 2014.000000, "casvol": 51.000000 }, "geometry": { "type": "Point", "coordinates": [ -80.548203013210284, 39.973300429604905 ] } },
{ "type": "Feature", "id": 35192, "properties": { "state": "West Virginia", "endyear": 2014.000000, "casvol": 33.000000 }, "geometry": { "type": "Point", "coordinates": [ -80.825482956504771, 39.242418378356383 ] } },
{ "type": "Feature", "id": 35193, "properties": { "state": "West Virginia", "endyear": 2014.000000, "casvol": 33.000000 }, "geometry": { "type": "Point", "coordinates": [ -80.548192016148704, 39.973178433126705 ] } },
{ "type": "Feature", "id": 35194, "properties": { "state": "West Virginia", "endyear": 2014.000000, "casvol": 39.000000 }, "geometry": { "type": "Point", "coordinates": [ -80.548195015121365, 39.973219431948799 ] } },
{ "type": "Feature", "id": 35195, "properties": { "state": "West Virginia", "endyear": 2014.000000, "casvol": 40.000000 }, "geometry": { "type": "Point", "coordinates": [ -80.53555598369708, 40.004174697321481 ] } },
{ "type": "Feature", "id": 35196, "properties": { "state": "West Virginia", "endyear": 2014.000000, "casvol": 42.000000 }, "geometry": { "type": "Point", "coordinates": [ -80.535601486576113, 40.004099698197528 ] } },
{ "type": "Feature", "id": 35203, "properties": { "state": "West Virginia", "endyear": 2014.000000, "casvol": 46.000000 }, "geometry": { "type": "Point", "coordinates": [ -80.786911619842741, 39.831572803521759 ] } },
{ "type": "Feature", "id": 35204, "properties": { "state": "West Virginia", "endyear": 2014.000000, "casvol": 20.000000 }, "geometry": { "type": "Point", "coordinates": [ -80.535603486123918, 40.004274695427966 ] } },
{ "type": "Feature", "id": 35205, "properties": { "state": "West Virginia", "endyear": 2014.000000, "casvol": 25.000000 }, "geometry": { "type": "Point", "coordinates": [ -80.535635488292371, 40.004177696741046 ] } },
{ "type": "Feature", "id": 35206, "properties": { "state": "West Virginia", "endyear": 2014.000000, "casvol": 29.000000 }, "geometry": { "type": "Point", "coordinates": [ -80.535618487434263, 40.004138697469273 ] } },
{ "type": "Feature", "id": 35207, "properties": { "state": "West Virginia", "endyear": 2014.000000, "casvol": 42.000000 }, "geometry": { "type": "Point", "coordinates": [ -80.548187017090967, 39.97313643434903 ] } },
{ "type": "Feature", "id": 35213, "properties": { "state": "West Virginia", "endyear": 2014.000000, "casvol": 43.000000 }, "geometry": { "type": "Point", "coordinates": [ -80.787130634612495, 39.831389803502084 ] } },
{ "type": "Feature", "id": 35214, "properties": { "state": "West Virginia", "endyear": 2014.000000, "casvol": 35.000000 }, "geometry": { "type": "Point", "coordinates": [ -80.535582485034098, 40.004235696183024 ] } },
{ "type": "Feature", "id": 35215, "properties": { "state": "West Virginia", "endyear": 2014.000000, "casvol": 37.000000 }, "geometry": { "type": "Point", "coordinates": [ -80.535573884610599, 40.004212696602934 ] } },
{ "type": "Feature", "id": 35216, "properties": { "state": "West Virginia", "endyear": 2014.000000, "casvol": 12.000000 }, "geometry": { "type": "Point", "coordinates": [ -80.575405053315606, 39.956208665616259 ] } },
{ "type": "Feature", "id": 35218, "properties": { "state": "West Virginia", "endyear": 2014.000000, "casvol": 31.000000 }, "geometry": { "type": "Point", "coordinates": [ -80.992817616831644, 39.335059592291543 ] } },
{ "type": "Feature", "id": 35219, "properties": { "state": "West Virginia", "endyear": 2014.000000, "casvol": 15.000000 }, "geometry": { "type": "Point", "coordinates": [ -80.575314050434017, 39.956128668575602 ] } },
{ "type": "Feature", "id": 35226, "properties": { "state": "West Virginia", "endyear": 2013.000000, "casvol": 18.000000 }, "geometry": { "type": "Point", "coordinates": [ -80.890192924242925, 39.191175021661152 ] } },
{ "type": "Feature", "id": 35227, "properties": { "state": "West Virginia", "endyear": 2013.000000, "casvol": 33.000000 }, "geometry": { "type": "Point", "coordinates": [ -80.890179023285867, 39.191094423800827 ] } },
{ "type": "Feature", "id": 35236, "properties": { "state": "West Virginia", "endyear": 2013.000000, "casvol": 0.000000 }, "geometry": { "type": "Point", "coordinates": [ -80.558717705196045, 39.384632994257004 ] } },
{ "type": "Feature", "id": 35251, "properties": { "state": "West Virginia", "endyear": 2014.000000, "casvol": 14.000000 }, "geometry": { "type": "Point", "coordinates": [ -80.738794374732962, 39.210432786702405 ] } },
{ "type": "Feature", "id": 35254, "properties": { "state": "West Virginia", "endyear": 2013.000000, "casvol": 0.000000 }, "geometry": { "type": "Point", "coordinates": [ -80.884233608800614, 39.195499436974764 ] } },
{ "type": "Feature", "id": 35255, "properties": { "state": "West Virginia", "endyear": 2013.000000, "casvol": 0.000000 }, "geometry": { "type": "Point", "coordinates": [ -80.884340011492625, 39.195505534768571 ] } },
{ "type": "Feature", "id": 35256, "properties": { "state": "West Virginia", "endyear": 2013.000000, "casvol": 0.000000 }, "geometry": { "type": "Point", "coordinates": [ -80.884303910584507, 39.195504135501551 ] } },
{ "type": "Feature", "id": 35265, "properties": { "state": "West Virginia", "endyear": 2013.000000, "casvol": 1.000000 }, "geometry": { "type": "Point", "coordinates": [ -80.919839950870923, 39.3340900010217 ] } },
{ "type": "Feature", "id": 49809, "properties": { "state": "West Virginia", "endyear": 2014.000000, "casvol": 4.000000 }, "geometry": { "type": "Point", "coordinates": [ -80.0367027, 39.2134652 ] } },
{ "type": "Feature", "id": 49810, "properties": { "state": "West Virginia", "endyear": 2014.000000, "casvol": 7.000000 }, "geometry": { "type": "Point", "coordinates": [ -80.037094, 39.213604 ] } },
{ "type": "Feature", "id": 49811, "properties": { "state": "West Virginia", "endyear": 2013.000000, "casvol": 16.000000 }, "geometry": { "type": "Point", "coordinates": [ -80.013458, 39.215603 ] } },
{ "type": "Feature", "id": 49812, "properties": { "state": "West Virginia", "endyear": 2014.000000, "casvol": 4.000000 }, "geometry": { "type": "Point", "coordinates": [ -80.036632, 39.2133828 ] } },
{ "type": "Feature", "id": 49814, "properties": { "state": "West Virginia", "endyear": 2013.000000, "casvol": 16.000000 }, "geometry": { "type": "Point", "coordinates": [ -80.013649, 39.215534 ] } },
{ "type": "Feature", "id": 49816, "properties": { "state": "West Virginia", "endyear": 2014.000000, "casvol": 25.000000 }, "geometry": { "type": "Point", "coordinates": [ -80.17223, 38.78725 ] } },
{ "type": "Feature", "id": 49820, "properties": { "state": "West Virginia", "endyear": 2014.000000, "casvol": 37.000000 }, "geometry": { "type": "Point", "coordinates": [ -80.172175, 38.7873361 ] } },
{ "type": "Feature", "id": 49821, "properties": { "state": "West Virginia", "endyear": 2014.000000, "casvol": 8.000000 }, "geometry": { "type": "Point", "coordinates": [ -80.0365967, 39.2133417 ] } },
{ "type": "Feature", "id": 49822, "properties": { "state": "West Virginia", "endyear": 2014.000000, "casvol": 7.000000 }, "geometry": { "type": "Point", "coordinates": [ -80.0366674, 39.213424 ] } },
{ "type": "Feature", "id": 49823, "properties": { "state": "West Virginia", "endyear": 2014.000000, "casvol": 10.000000 }, "geometry": { "type": "Point", "coordinates": [ -80.036756, 39.213506 ] } },
{ "type": "Feature", "id": 49824, "properties": { "state": "West Virginia", "endyear": 2014.000000, "casvol": 5.000000 }, "geometry": { "type": "Point", "coordinates": [ -80.587027, 39.079232 ] } },
{ "type": "Feature", "id": 49825, "properties": { "state": "West Virginia", "endyear": 2014.000000, "casvol": 8.000000 }, "geometry": { "type": "Point", "coordinates": [ -80.055462, 39.1955658 ] } },
{ "type": "Feature", "id": 49826, "properties": { "state": "West Virginia", "endyear": 2015.000000, "casvol": 8.000000 }, "geometry": { "type": "Point", "coordinates": [ -80.0555149, 39.1955383 ] } },
{ "type": "Feature", "id": 49827, "properties": { "state": "West Virginia", "endyear": 2015.000000, "casvol": 10.000000 }, "geometry": { "type": "Point", "coordinates": [ -80.0556207, 39.1954834 ] } },
{ "type": "Feature", "id": 49828, "properties": { "state": "West Virginia", "endyear": 2015.000000, "casvol": 7.000000 }, "geometry": { "type": "Point", "coordinates": [ -80.0555944, 39.1955167 ] } },
{ "type": "Feature", "id": 49829, "properties": { "state": "West Virginia", "endyear": 2015.000000, "casvol": 12.000000 }, "geometry": { "type": "Point", "coordinates": [ -80.7636111, 39.1707778 ] } },
{ "type": "Feature", "id": 49830, "properties": { "state": "West Virginia", "endyear": 2015.000000, "casvol": 14.000000 }, "geometry": { "type": "Point", "coordinates": [ -80.7636389, 39.17075 ] } },
{ "type": "Feature", "id": 49834, "properties": { "state": "West Virginia", "endyear": 2015.000000, "casvol": 0.000000 }, "geometry": { "type": "Point", "coordinates": [ -80.15213, 39.704419 ] } },
{ "type": "Feature", "id": 49835, "properties": { "state": "West Virginia", "endyear": 2014.000000, "casvol": 0.000000 }, "geometry": { "type": "Point", "coordinates": [ -80.152517, 39.704281 ] } },
{ "type": "Feature", "id": 49836, "properties": { "state": "West Virginia", "endyear": 2014.000000, "casvol": 0.000000 }, "geometry": { "type": "Point", "coordinates": [ -80.152388, 39.704327 ] } },
{ "type": "Feature", "id": 49837, "properties": { "state": "West Virginia", "endyear": 2015.000000, "casvol": 0.000000 }, "geometry": { "type": "Point", "coordinates": [ -80.152259, 39.704373 ] } },
{ "type": "Feature", "id": 49895, "properties": { "state": "West Virginia", "endyear": 2014.000000, "casvol": 1.000000 }, "geometry": { "type": "Point", "coordinates": [ -80.732797, 39.365881 ] } },
{ "type": "Feature", "id": 49901, "properties": { "state": "West Virginia", "endyear": 2014.000000, "casvol": 25.000000 }, "geometry": { "type": "Point", "coordinates": [ -80.848731, 39.2747 ] } },
{ "type": "Feature", "id": 49911, "properties": { "state": "West Virginia", "endyear": 2013.000000, "casvol": 49.000000 }, "geometry": { "type": "Point", "coordinates": [ -80.52945, 39.9775 ] } },
{ "type": "Feature", "id": 49913, "properties": { "state": "West Virginia", "endyear": 2015.000000, "casvol": 15.000000 }, "geometry": { "type": "Point", "coordinates": [ -80.673017, 39.285225 ] } },
{ "type": "Feature", "id": 49914, "properties": { "state": "West Virginia", "endyear": 2015.000000, "casvol": 18.000000 }, "geometry": { "type": "Point", "coordinates": [ -80.673042, 39.285242 ] } },
{ "type": "Feature", "id": 49964, "properties": { "state": "West Virginia", "endyear": 2013.000000, "casvol": 25.000000 }, "geometry": { "type": "Point", "coordinates": [ -80.53532, 39.95549 ] } },
{ "type": "Feature", "id": 49965, "properties": { "state": "West Virginia", "endyear": 2013.000000, "casvol": 27.000000 }, "geometry": { "type": "Point", "coordinates": [ -80.53539, 39.95551 ] } },
{ "type": "Feature", "id": 49966, "properties": { "state": "West Virginia", "endyear": 2013.000000, "casvol": 26.000000 }, "geometry": { "type": "Point", "coordinates": [ -80.53537, 39.95556 ] } },
{ "type": "Feature", "id": 49967, "properties": { "state": "West Virginia", "endyear": 2013.000000, "casvol": 27.000000 }, "geometry": { "type": "Point", "coordinates": [ -80.53544, 39.95557 ] } },
{ "type": "Feature", "id": 49968, "properties": { "state": "West Virginia", "endyear": 2013.000000, "casvol": 13.000000 }, "geometry": { "type": "Point", "coordinates": [ -80.53558, 39.9556 ] } },
{ "type": "Feature", "id": 49969, "properties": { "state": "West Virginia", "endyear": 2013.000000, "casvol": 12.000000 }, "geometry": { "type": "Point", "coordinates": [ -80.5356, 39.95556 ] } },
{ "type": "Feature", "id": 49970, "properties": { "state": "West Virginia", "endyear": 2013.000000, "casvol": 12.000000 }, "geometry": { "type": "Point", "coordinates": [ -80.53553, 39.95554 ] } },
{ "type": "Feature", "id": 49971, "properties": { "state": "West Virginia", "endyear": 2013.000000, "casvol": 27.000000 }, "geometry": { "type": "Point", "coordinates": [ -80.53546, 39.95552 ] } },
{ "type": "Feature", "id": 49972, "properties": { "state": "West Virginia", "endyear": 2013.000000, "casvol": 17.000000 }, "geometry": { "type": "Point", "coordinates": [ -80.53526, 39.95539 ] } },
{ "type": "Feature", "id": 49973, "properties": { "state": "West Virginia", "endyear": 2013.000000, "casvol": 24.000000 }, "geometry": { "type": "Point", "coordinates": [ -80.94561, 38.84891 ] } },
{ "type": "Feature", "id": 49974, "properties": { "state": "West Virginia", "endyear": 2013.000000, "casvol": 20.000000 }, "geometry": { "type": "Point", "coordinates": [ -80.94564, 38.94895 ] } },
{ "type": "Feature", "id": 49975, "properties": { "state": "West Virginia", "endyear": 2013.000000, "casvol": 23.000000 }, "geometry": { "type": "Point", "coordinates": [ -80.53526, 39.95547 ] } },
{ "type": "Feature", "id": 49976, "properties": { "state": "West Virginia", "endyear": 2013.000000, "casvol": 16.000000 }, "geometry": { "type": "Point", "coordinates": [ -80.5355, 39.95559 ] } },
{ "type": "Feature", "id": 49977, "properties": { "state": "West Virginia", "endyear": 2013.000000, "casvol": 44.000000 }, "geometry": { "type": "Point", "coordinates": [ -80.52914, 39.97744 ] } },
{ "type": "Feature", "id": 49978, "properties": { "state": "West Virginia", "endyear": 2013.000000, "casvol": 41.000000 }, "geometry": { "type": "Point", "coordinates": [ -80.52926, 39.97747 ] } },
{ "type": "Feature", "id": 49979, "properties": { "state": "West Virginia", "endyear": 2013.000000, "casvol": 37.000000 }, "geometry": { "type": "Point", "coordinates": [ -80.5292, 39.97745 ] } },
{ "type": "Feature", "id": 49980, "properties": { "state": "West Virginia", "endyear": 2013.000000, "casvol": 43.000000 }, "geometry": { "type": "Point", "coordinates": [ -80.52932, 39.97748 ] } },
{ "type": "Feature", "id": 49981, "properties": { "state": "West Virginia", "endyear": 2013.000000, "casvol": 43.000000 }, "geometry": { "type": "Point", "coordinates": [ -80.52945, 39.97751 ] } },
{ "type": "Feature", "id": 49982, "properties": { "state": "West Virginia", "endyear": 2012.000000, "casvol": 0.000000 }, "geometry": { "type": "Point", "coordinates": [ -80.419572, 39.303572 ] } },
{ "type": "Feature", "id": 49983, "properties": { "state": "West Virginia", "endyear": 2014.000000, "casvol": 0.000000 }, "geometry": { "type": "Point", "coordinates": [ -80.489517, 39.201631 ] } },
{ "type": "Feature", "id": 49984, "properties": { "state": "West Virginia", "endyear": 2014.000000, "casvol": 0.000000 }, "geometry": { "type": "Point", "coordinates": [ -80.489492, 39.201611 ] } },
{ "type": "Feature", "id": 49996, "properties": { "state": "West Virginia", "endyear": 2014.000000, "casvol": 17.000000 }, "geometry": { "type": "Point", "coordinates": [ -80.690122, 39.324289 ] } },
{ "type": "Feature", "id": 49997, "properties": { "state": "West Virginia", "endyear": 2014.000000, "casvol": 25.000000 }, "geometry": { "type": "Point", "coordinates": [ -80.848731, 39.2747 ] } },
{ "type": "Feature", "id": 49998, "properties": { "state": "West Virginia", "endyear": 2014.000000, "casvol": 17.000000 }, "geometry": { "type": "Point", "coordinates": [ -80.690133, 39.324317 ] } },
{ "type": "Feature", "id": 49999, "properties": { "state": "West Virginia", "endyear": 2014.000000, "casvol": 13.000000 }, "geometry": { "type": "Point", "coordinates": [ -80.738889, 39.210331 ] } },
{ "type": "Feature", "id": 50000, "properties": { "state": "West Virginia", "endyear": 2014.000000, "casvol": 19.000000 }, "geometry": { "type": "Point", "coordinates": [ -80.822733, 39.303975 ] } },
{ "type": "Feature", "id": 50001, "properties": { "state": "West Virginia", "endyear": 2014.000000, "casvol": 19.000000 }, "geometry": { "type": "Point", "coordinates": [ -80.822722, 39.303994 ] } },
{ "type": "Feature", "id": 50008, "properties": { "state": "West Virginia", "endyear": 2014.000000, "casvol": 14.000000 }, "geometry": { "type": "Point", "coordinates": [ -80.738992, 39.210358 ] } },
{ "type": "Feature", "id": 50009, "properties": { "state": "West Virginia", "endyear": 2014.000000, "casvol": 27.000000 }, "geometry": { "type": "Point", "coordinates": [ -80.740992, 39.202603 ] } },
{ "type": "Feature", "id": 50010, "properties": { "state": "West Virginia", "endyear": 2014.000000, "casvol": 23.000000 }, "geometry": { "type": "Point", "coordinates": [ -80.993058, 39.365339 ] } },
{ "type": "Feature", "id": 50013, "properties": { "state": "West Virginia", "endyear": 2014.000000, "casvol": 1.000000 }, "geometry": { "type": "Point", "coordinates": [ -80.858794, 39.4521 ] } },
{ "type": "Feature", "id": 50014, "properties": { "state": "West Virginia", "endyear": 2014.000000, "casvol": 19.000000 }, "geometry": { "type": "Point", "coordinates": [ -80.690111, 39.324261 ] } },
{ "type": "Feature", "id": 50040, "properties": { "state": "West Virginia", "endyear": 2015.000000, "casvol": 0.000000 }, "geometry": { "type": "Point", "coordinates": [ -80.69011, 39.324342 ] } },
{ "type": "Feature", "id": 50041, "properties": { "state": "West Virginia", "endyear": 2014.000000, "casvol": 1.000000 }, "geometry": { "type": "Point", "coordinates": [ -80.721211, 39.363286 ] } },
{ "type": "Feature", "id": 50042, "properties": { "state": "West Virginia", "endyear": 2014.000000, "casvol": 0.000000 }, "geometry": { "type": "Point", "coordinates": [ -80.721142, 39.363303 ] } },
{ "type": "Feature", "id": 50043, "properties": { "state": "West Virginia", "endyear": 2014.000000, "casvol": 35.000000 }, "geometry": { "type": "Point", "coordinates": [ -80.741025, 39.202611 ] } },
{ "type": "Feature", "id": 50044, "properties": { "state": "West Virginia", "endyear": 2015.000000, "casvol": 15.000000 }, "geometry": { "type": "Point", "coordinates": [ -80.672994, 39.285197 ] } },
{ "type": "Feature", "id": 50046, "properties": { "state": "West Virginia", "endyear": 2014.000000, "casvol": 0.000000 }, "geometry": { "type": "Point", "coordinates": [ -80.489492, 39.201611 ] } }
]
}
